{"status":"done","publicPath":"http://localhost:8080/","chunks":{"chunk-vendors":[{"name":"js/chunk-vendors.js","publicPath":"http://localhost:8080/js/chunk-vendors.js","path":"/Users/chapkovski/Documents/gettiernew/_static/vue/js/chunk-vendors.js"}],"main":[{"name":"js/main.js","publicPath":"http://localhost:8080/js/main.js","path":"/Users/chapkovski/Documents/gettiernew/_static/vue/js/main.js"},{"name":"main.06d2409c1430f080370e.hot-update.js","publicPath":"http://localhost:8080/main.06d2409c1430f080370e.hot-update.js","path":"/Users/chapkovski/Documents/gettiernew/_static/vue/main.06d2409c1430f080370e.hot-update.js"}],"no_chat":[{"name":"js/no_chat.js","publicPath":"http://localhost:8080/js/no_chat.js","path":"/Users/chapkovski/Documents/gettiernew/_static/vue/js/no_chat.js"}],"vignette":[{"name":"js/vignette.js","publicPath":"http://localhost:8080/js/vignette.js","path":"/Users/chapkovski/Documents/gettiernew/_static/vue/js/vignette.js"}]},"error":"ModuleBuildError","message":"Module build failed (from ./node_modules/postcss-loader/src/index.js):\nSyntaxError\n\n(153:1) Unexpected }\n\n  151 |   display: flex;\n  152 |   flex-direction: column;\n> 153 | }\n      | ^\n  154 | .content-col {\n  155 |   /* height: calc(100vh) !important; */\n"}